FSMs'/odd_even_parity/o_e_parity.v
module o_e_parity(x,clk,z);
input x,clk;
output reg z;
reg even_odd;
parameter EVEN=0, ODD=1;

always @(posedge clk)
case(even_odd)
	EVEN: begin
		z<=x?1:0; //If X==1, then z==1 else z==0
		even_odd<=x?ODD:EVEN;
	end
	ODD: begin
		z<=x?0:1;	//if x==1, then z=0 else z==1
		even_odd<=x?EVEN:ODD;
	end
	default: even_odd<=EVEN;
	endcase
	endmodule

FSMs'/odd_even_parity/o_e_parity_tb.v
module o_e_parity_testbench;
reg clk,x; wire z;
reg correct=1;

o_e_parity inst_1(x,clk,z);

initial begin
clk=1'b0;
$dumpfile("o_e_parity_check.vcd"); $dumpvars(0,o_e_parity_testbench);
end

always #5 clk=~clk;

initial begin   // this way circuit can be verified.!
	#2 x=0; #10 x=1; 
	if(z!=0) correct=0;
	#10 x=1; 
	if(z!=1) correct=0;
	#10 x=1;
	if(z!=0) correct=0;
	#10 x=0; #10 x=1; 
	if(z!=1) correct=0;
	#10 x=1;
	if(z!=0) correct=0;
	#10 x=0;

	if(correct==1) $display("\t\t\tCircuit working as expected.!");
	else $display(" ERROR.! Recheck the design module file.!");

	#10 $finish;
end

endmodule

FSMs'/odd_even_parity/o_e_parity_check.vcd
$date
	Thu Jan 30 21:45:02 2020
$end
$version
	Icarus Verilog
$end
$timescale
	1s
$end
$scope module o_e_parity_testbench $end
$var wire 1 ! z $end
$var reg 1 " clk $end
$var reg 1 # correct $end
$var reg 1 $ x $end
$scope module inst_1 $end
$var wire 1 " clk $end
$var wire 1 $ x $end
$var reg 1 % even_odd $end
$var reg 1 ! z $end
$upscope $end
$upscope $end
$enddefinitions $end
#0
$dumpvars
x%
x$
1#
0"
x!
$end
#2
0$
#5
0%
1"
#10
0"
#12
1$
#15
1%
1!
1"
#20
0"
#25
0%
0!
1"
#30
0"
#35
1%
1!
1"
#40
0"
#42
0$
#45
1"
#50
0"
#52
1$
#55
0%
0!
1"
#60
0"
#65
1%
1!
1"
#70
0"
#72
0$
