FSMs'/sequence_detector/overlapping_case/seq_dec_ov.v
//Check this module

module seq_dec_ov(clk,x,z,reset);
input clk,x,reset;
output reg z;
reg[1:0] state_name,present_state;
parameter S_0=2'b00,S_1=2'b01,S_2=2'b10,S_3=2'b11;
	
always @(posedge clk)
	case(present_state)
		S_0: begin
		z=0;
		state_name=x?S_0:S_1;
		end
		S_1:begin z=0;
		state_name=x?S_2:S_1;end
		S_2: begin z=0;
		state_name=x?S_1:S_1;end
		S_3:begin 
		z=x?0:1;
		state_name=x?S_0:S_1;end
		default: begin
		state_name=S_0;
		z=0;
		end
	endcase

endmodule

FSMs'/sequence_detector/overlapping_case/seq_dec_ov_tb.v
module seq_dec_ov_tb;
reg clk,x,reset;
wire z;

seq_dec_ov inst_1(clk,x,z,reset);
initial begin
	clk=1'b0;
	$dumpfile("seq_dec_ov_waveform.vcd"); $dumpvars(0,seq_dec_ov_tb);
end
always #5 clk=~clk;

initial begin
	#12 x=1; #10 x=0; #10 x=1; #10 x=1; 		//1011
	#10 x=0; #10 x=1; #10 x=0; #10 x=0;			//0100
	#10 x=1; #10 x=1; #10 x=0;					//110
	$display("Check the vcd file for verification");
	#20 $finish;
end
endmodule

FSMs'/sequence_detector/overlapping_case/seq_dec_ov_waveform.vcd
$date
	Fri Jan 31 09:18:14 2020
$end
$version
	Icarus Verilog
$end
$timescale
	1s
$end
$scope module seq_dec_ov_tb $end
$var wire 1 ! z $end
$var reg 1 " clk $end
$var reg 1 # reset $end
$var reg 1 $ x $end
$scope module inst_1 $end
$var wire 1 " clk $end
$var wire 1 # reset $end
$var wire 1 $ x $end
$var reg 2 % present_state [1:0] $end
$var reg 2 & state_name [1:0] $end
$var reg 1 ! z $end
$upscope $end
$upscope $end
$enddefinitions $end
#0
$dumpvars
bx &
bx %
x$
x#
0"
x!
$end
#5
0!
b0 &
1"
#10
0"
#12
1$
#15
1"
#20
0"
#22
0$
#25
1"
#30
0"
#32
1$
#35
1"
#40
0"
#45
1"
#50
0"
#52
0$
#55
1"
#60
0"
#62
1$
#65
1"
#70
0"
#72
0$
#75
1"
#80
0"
#85
1"
#90
0"
#92
1$
#95
1"
#100
0"
#105
1"
#110
0"
#112
0$
