Add_Sub/Half_adder/ha.v
module ha(A,B,S,C);
input A,B;
output S,C;
assign S=A^B;
assign C=A&B;
endmodule

Add_Sub/Full_adder/fa.v
module fa(A,B,C,Sum,Carry);
input A,B,C;
wire x,y,z;
output Sum,Carry;


ha inst_1(.A(A),.B(B),.S(x),.C(y));
ha inst_2(.A(C),.B(x),.S(Sum),.C(z));
assign Carry= y|z;

endmodule

Add_Sub/Full_adder/fa_tb.v
module testbench;
reg x,y,z; wire s,c;
integer i;
fa DUT(.A(x),.B(y),.C(z),.Sum(s),.Carry(c));

initial begin
$dumpfile("full_adder.vcd");
$dumpvars(0,testbench);

for(i=0;i<8;i=i+1) begin
	#5 {x,y,z}=i;
	#2 $display(" X= %b, Y=%b, Z=%b S=%b, C=%b",x,y,z,s,c);
end
#10 $finish;
 end
endmodule

Add_Sub/Full_adder/full_adder.vcd
$date
	Mon Feb 10 22:19:32 2020
$end
$version
	Icarus Verilog
$end
$timescale
	1s
$end
$scope module testbench $end
$var wire 1 ! s $end
$var wire 1 " c $end
$var reg 1 # x $end
$var reg 1 $ y $end
$var reg 1 % z $end
$var integer 32 & i [31:0] $end
$scope module DUT $end
$var wire 1 # A $end
$var wire 1 $ B $end
$var wire 1 % C $end
$var wire 1 " Carry $end
$var wire 1 ' z $end
$var wire 1 ( y $end
$var wire 1 ) x $end
$var wire 1 ! Sum $end
$scope module inst_1 $end
$var wire 1 # A $end
$var wire 1 $ B $end
$var wire 1 ( C $end
$var wire 1 ) S $end
$upscope $end
$scope module inst_2 $end
$var wire 1 % A $end
$var wire 1 ) B $end
$var wire 1 ' C $end
$var wire 1 ! S $end
$upscope $end
$upscope $end
$upscope $end
$enddefinitions $end
#0
$dumpvars
x)
x(
x'
b0 &
x%
x$
x#
x"
x!
$end
#5
0!
0"
0)
0(
0'
0#
0$
0%
#7
b1 &
#12
1!
1%
#14
b10 &
#19
1)
1!
1$
0%
#21
b11 &
#26
1"
0!
1'
1%
#28
b100 &
#33
0"
1!
0'
1#
0$
0%
#35
b101 &
#40
1"
0!
1'
1%
#42
b110 &
#47
0)
1(
0!
0'
1$
0%
#49
b111 &
#54
1!
1%
#56
b1000 &
