FSMs'/sequence_detector/non_overlapping_case/seq_dec_nov.v
//Check this module

module seq_dec_nov(clk,x,z);
input clk,x;
output reg z;
reg[1:0] state_name;
parameter S_0=2'b00,S_1=2'b01,S_2=2'b10,S_3=2'b11;

always @(posedge clk)
	case(state_name)
		S_0: begin
		z<=0;
		state_name<=x?S_1:S_0;
		end
		S_1:begin z<=0;
		state_name<=x?S_0:S_2;end
		S_2: begin z<=0;
		state_name<=x?S_0:S_3;end
		S_3:begin 
		z<=x?1:0;
		state_name<=S_0;end
		default: begin
		state_name<=S_0;
		z<=0;
		end
	endcase

endmodule

FSMs'/sequence_detector/non_overlapping_case/seq_dev_nov_tb.v
module seq_dec_nov_tb;
reg clk,x;
wire z;

seq_dec_nov inst_1(clk,x,z);
initial begin
	clk=1'b0;
	$dumpfile("seq_dec_nov_waveform.vcd"); $dumpvars(0,seq_dec_nov_tb);
end
always #5 clk=~clk;

initial begin
	#12 x=1; #10 x=0; #10 x=1; #10 x=1; //1011
	#10 x=0; #10 x=1; #10 x=0; #10 x=0;			//0100
	#10 x=1; #10 x=1; #10 x=0;					//110
	$display("Check the vcd file for verification");
	#20 $finish;
end
endmodule

FSMs'/sequence_detector/non_overlapping_case/seq_dec_nov_waveform.vcd
$date
	Thu Jan 30 22:32:01 2020
$end
$version
	Icarus Verilog
$end
$timescale
	1s
$end
$scope module seq_dec_nov_tb $end
$var wire 1 ! z $end
$var reg 1 " clk $end
$var reg 1 # x $end
$scope module inst_1 $end
$var wire 1 " clk $end
$var wire 1 # x $end
$var reg 2 $ state_name [1:0] $end
$var reg 1 ! z $end
$upscope $end
$upscope $end
$enddefinitions $end
#0
$dumpvars
bx $
x#
0"
x!
$end
#5
0!
b0 $
1"
#10
0"
#12
1#
#15
b1 $
1"
#20
0"
#22
0#
#25
b10 $
1"
#30
0"
#32
1#
#35
b0 $
1"
#40
0"
#45
b1 $
1"
#50
0"
#52
0#
#55
b10 $
1"
#60
0"
#62
1#
#65
b0 $
1"
#70
0"
#72
0#
#75
1"
#80
0"
#85
1"
#90
0"
#92
1#
#95
b1 $
1"
#100
0"
#105
b0 $
1"
#110
0"
#112
0#
